{
    "?xml-stylesheet": "href=\"file:///D:/nmap/nmap.xsl\" type=\"text/xsl\"",
    "nmaprun": {
      "-start": "1647456596",
      "-profile_name": "Intense scan",
      "-xmloutputversion": "1.04",
      "-scanner": "nmap",
      "-version": "7.92",
      "-startstr": "Thu Mar 17 01:49:56 2022",
      "-args": "nmap -T4 -A -v 161.200.116.30",
      "scaninfo": {
        "-services": "1,3-4,6-7,9,13,17,19-26,30,32-33,37,42-43,49,53,70,79-85,88-90,99-100,106,109-111,113,119,125,135,139,143-144,146,161,163,179,199,211-212,222,254-256,259,264,280,301,306,311,340,366,389,406-407,416-417,425,427,443-445,458,464-465,481,497,500,512-515,524,541,543-545,548,554-555,563,587,593,616-617,625,631,636,646,648,666-668,683,687,691,700,705,711,714,720,722,726,749,765,777,783,787,800-801,808,843,873,880,888,898,900-903,911-912,981,987,990,992-993,995,999-1002,1007,1009-1011,1021-1100,1102,1104-1108,1110-1114,1117,1119,1121-1124,1126,1130-1132,1137-1138,1141,1145,1147-1149,1151-1152,1154,1163-1166,1169,1174-1175,1183,1185-1187,1192,1198-1199,1201,1213,1216-1218,1233-1234,1236,1244,1247-1248,1259,1271-1272,1277,1287,1296,1300-1301,1309-1311,1322,1328,1334,1352,1417,1433-1434,1443,1455,1461,1494,1500-1501,1503,1521,1524,1533,1556,1580,1583,1594,1600,1641,1658,1666,1687-1688,1700,1717-1721,1723,1755,1761,1782-1783,1801,1805,1812,1839-1840,1862-1864,1875,1900,1914,1935,1947,1971-1972,1974,1984,1998-2010,2013,2020-2022,2030,2033-2035,2038,2040-2043,2045-2049,2065,2068,2099-2100,2103,2105-2107,2111,2119,2121,2126,2135,2144,2160-2161,2170,2179,2190-2191,2196,2200,2222,2251,2260,2288,2301,2323,2366,2381-2383,2393-2394,2399,2401,2492,2500,2522,2525,2557,2601-2602,2604-2605,2607-2608,2638,2701-2702,2710,2717-2718,2725,2800,2809,2811,2869,2875,2909-2910,2920,2967-2968,2998,3000-3001,3003,3005-3007,3011,3013,3017,3030-3031,3052,3071,3077,3128,3168,3211,3221,3260-3261,3268-3269,3283,3300-3301,3306,3322-3325,3333,3351,3367,3369-3372,3389-3390,3404,3476,3493,3517,3527,3546,3551,3580,3659,3689-3690,3703,3737,3766,3784,3800-3801,3809,3814,3826-3828,3851,3869,3871,3878,3880,3889,3905,3914,3918,3920,3945,3971,3986,3995,3998,4000-4006,4045,4111,4125-4126,4129,4224,4242,4279,4321,4343,4443-4446,4449,4550,4567,4662,4848,4899-4900,4998,5000-5004,5009,5030,5033,5050-5051,5054,5060-5061,5080,5087,5100-5102,5120,5190,5200,5214,5221-5222,5225-5226,5269,5280,5298,5357,5405,5414,5431-5432,5440,5500,5510,5544,5550,5555,5560,5566,5631,5633,5666,5678-5679,5718,5730,5800-5802,5810-5811,5815,5822,5825,5850,5859,5862,5877,5900-5904,5906-5907,5910-5911,5915,5922,5925,5950,5952,5959-5963,5987-5989,5998-6007,6009,6025,6059,6100-6101,6106,6112,6123,6129,6156,6346,6389,6502,6510,6543,6547,6565-6567,6580,6646,6666-6669,6689,6692,6699,6779,6788-6789,6792,6839,6881,6901,6969,7000-7002,7004,7007,7019,7025,7070,7100,7103,7106,7200-7201,7402,7435,7443,7496,7512,7625,7627,7676,7741,7777-7778,7800,7911,7920-7921,7937-7938,7999-8002,8007-8011,8021-8022,8031,8042,8045,8080-8090,8093,8099-8100,8180-8181,8192-8194,8200,8222,8254,8290-8292,8300,8333,8383,8400,8402,8443,8500,8600,8649,8651-8652,8654,8701,8800,8873,8888,8899,8994,9000-9003,9009-9011,9040,9050,9071,9080-9081,9090-9091,9099-9103,9110-9111,9200,9207,9220,9290,9415,9418,9485,9500,9502-9503,9535,9575,9593-9595,9618,9666,9876-9878,9898,9900,9917,9929,9943-9944,9968,9998-10004,10009-10010,10012,10024-10025,10082,10180,10215,10243,10566,10616-10617,10621,10626,10628-10629,10778,11110-11111,11967,12000,12174,12265,12345,13456,13722,13782-13783,14000,14238,14441-14442,15000,15002-15004,15660,15742,16000-16001,16012,16016,16018,16080,16113,16992-16993,17877,17988,18040,18101,18988,19101,19283,19315,19350,19780,19801,19842,20000,20005,20031,20221-20222,20828,21571,22939,23502,24444,24800,25734-25735,26214,27000,27352-27353,27355-27356,27715,28201,30000,30718,30951,31038,31337,32768-32785,33354,33899,34571-34573,35500,38292,40193,40911,41511,42510,44176,44442-44443,44501,45100,48080,49152-49161,49163,49165,49167,49175-49176,49400,49999-50003,50006,50300,50389,50500,50636,50800,51103,51493,52673,52822,52848,52869,54045,54328,55055-55056,55555,55600,56737-56738,57294,57797,58080,60020,60443,61532,61900,62078,63331,64623,64680,65000,65129,65389",
        "-protocol": "tcp",
        "-numservices": "1000",
        "-type": "syn"
      },
      "verbose": {
        "-level": "1"
      },
      "debugging": {
        "-level": "0"
      },
      "output": {
        "-type": "interactive",
        "#text": "Starting Nmap 7.92 ( https://nmap.org ) at 2022-03-17 01:49 SE Asia Standard Time\n\nNSE: Loaded 155 scripts for scanning.\n\nNSE: Script Pre-scanning.\n\nInitiating NSE at 01:49\n\nCompleted NSE at 01:49, 0.00s elapsed\n\nInitiating NSE at 01:49\n\nCompleted NSE at 01:49, 0.00s elapsed\n\nInitiating NSE at 01:49\n\nCompleted NSE at 01:49, 0.00s elapsed\n\nInitiating Ping Scan at 01:49\n\nScanning 161.200.116.30 [4 ports]\n\nCompleted Ping Scan at 01:49, 0.02s elapsed (1 total hosts)\n\nInitiating Parallel DNS resolution of 1 host. at 01:49\n\nCompleted Parallel DNS resolution of 1 host. at 01:49, 0.03s elapsed\n\nInitiating SYN Stealth Scan at 01:49\n\nScanning 161.200.116.30 [1000 ports]\n\nDiscovered open port 443/tcp on 161.200.116.30\n\nDiscovered open port 53/tcp on 161.200.116.30\n\nDiscovered open port 80/tcp on 161.200.116.30\n\nDiscovered open port 22/tcp on 161.200.116.30\n\nCompleted SYN Stealth Scan at 01:50, 4.40s elapsed (1000 total ports)\n\nInitiating Service scan at 01:50\n\nScanning 4 services on 161.200.116.30\n\nCompleted Service scan at 01:50, 12.10s elapsed (4 services on 1 host)\n\nInitiating OS detection (try #1) against 161.200.116.30\n\nRetrying OS detection (try #2) against 161.200.116.30\n\nInitiating Traceroute at 01:50\n\nCompleted Traceroute at 01:50, 0.03s elapsed\n\nInitiating Parallel DNS resolution of 5 hosts. at 01:50\n\nCompleted Parallel DNS resolution of 5 hosts. at 01:50, 0.01s elapsed\n\nNSE: Script scanning 161.200.116.30.\n\nInitiating NSE at 01:50\n\nCompleted NSE at 01:50, 8.13s elapsed\n\nInitiating NSE at 01:50\n\nCompleted NSE at 01:50, 0.14s elapsed\n\nInitiating NSE at 01:50\n\nCompleted NSE at 01:50, 0.00s elapsed\n\nNmap scan report for 161.200.116.30\n\nHost is up (0.0055s latency).\n\nNot shown: 980 filtered tcp ports (no-response), 5 filtered tcp ports (admin-prohibited)\n\nPORT     STATE  SERVICE       VERSION\n\n21/tcp   closed ftp\n\n22/tcp   open   ssh           OpenSSH 7.9p1 Debian 10+deb10u2 (protocol 2.0)\n\n| ssh-hostkey: \n\n|   2048 98:2c:73:1a:c2:f2:a3:98:94:05:39:0e:e7:f8:cd:5c (RSA)\n\n|   256 ff:89:be:c3:8d:c6:16:0d:97:87:60:5a:13:4d:0e:f7 (ECDSA)\n\n|_  256 1a:a2:28:16:6a:92:b1:fe:f5:fb:60:3d:5d:35:aa:ce (ED25519)\n\n43/tcp   closed whois\n\n53/tcp   open   domain        ISC BIND 9.11.5-P4-5.1+deb10u1 (Debian Linux)\n\n| dns-nsid: \n\n|_  bind.version: 9.11.5-P4-5.1+deb10u1-Debian\n\n79/tcp   closed finger\n\n80/tcp   open   http          OpenResty web app server 1.15.8.1\n\n|_http-title: Site doesn't have a title (text/plain; charset=utf-8).\n\n|_http-server-header: openresty/1.15.8.1\n\n110/tcp  closed pop3\n\n119/tcp  closed nntp\n\n143/tcp  closed imap\n\n443/tcp  open   ssl/http      OpenResty web app server 1.15.8.1\n\n|_http-title: Site doesn't have a title (text/plain; charset=utf-8).\n\n|_http-server-header: openresty/1.15.8.1\n\n| ssl-cert: Subject: commonName=Kubernetes Ingress Controller Fake Certificate/organizationName=Acme Co\n\n| Subject Alternative Name: DNS:ingress.local\n\n| Issuer: commonName=Kubernetes Ingress Controller Fake Certificate/organizationName=Acme Co\n\n| Public Key type: rsa\n\n| Public Key bits: 2048\n\n| Signature Algorithm: sha256WithRSAEncryption\n\n| Not valid before: 2022-02-27T08:34:25\n\n| Not valid after:  2023-02-27T08:34:25\n\n| MD5:   010e 28df 41de 16cc c9b4 c26c 38a5 93d0\n\n|_SHA-1: 3ffa 855c 4427 eb88 3659 8f09 89d2 5d26 80ed a686\n\n993/tcp  closed imaps\n\n995/tcp  closed pop3s\n\n3389/tcp closed ms-wbt-server\n\n6668/tcp closed irc\n\n6669/tcp closed irc\n\nOS fingerprint not ideal because: Didn't receive UDP response. Please try again with -sSU\n\nNo OS matches for host\n\nUptime guess: 8.998 days (since Tue Mar  8 01:53:53 2022)\n\nNetwork Distance: 5 hops\n\nTCP Sequence Prediction: Difficulty=262 (Good luck!)\n\nIP ID Sequence Generation: All zeros\n\nService Info: OS: Linux; CPE: cpe:/o:linux:linux_kernel\n\n\n\nTRACEROUTE (using port 80/tcp)\n\nHOP RTT     ADDRESS\n\n1   2.00 ms 192.168.1.1\n\n2   6.00 ms 100.96.0.1\n\n3   5.00 ms eth13.bpi.tls1b-bcr01.myaisfibre.com (49.228.2.42)\n\n4   5.00 ms ae22.bgw01j.tls1a.myaisfibre.com (49.228.6.28)\n\n5   5.00 ms 161.200.116.30\n\n\n\nNSE: Script Post-scanning.\n\nInitiating NSE at 01:50\n\nCompleted NSE at 01:50, 0.00s elapsed\n\nInitiating NSE at 01:50\n\nCompleted NSE at 01:50, 0.00s elapsed\n\nInitiating NSE at 01:50\n\nCompleted NSE at 01:50, 0.00s elapsed\n\nRead data files from: D:\\nmap\n\nOS and Service detection performed. Please report any incorrect results at https://nmap.org/submit/ .\n\nNmap done: 1 IP address (1 host up) scanned in 31.73 seconds\n\n           Raw packets sent: 2062 (94.788KB) | Rcvd: 79 (4.534KB)\n\n"
      },
      "host": {
        "-comment": "",
        "status": {
          "-state": "up"
        },
        "address": {
          "-addrtype": "ipv4",
          "-vendor": "",
          "-addr": "161.200.116.30"
        },
        "hostnames": {
        },
        "ports": {
          "extraports": {
            "-count": "985",
            "-state": "filtered"
          },
          "port": [
            {
              "-protocol": "tcp",
              "-portid": "21",
              "state": {
                "-reason": "reset",
                "-state": "closed",
                "-reason_ttl": "45"
              },
              "service": {
                "-method": "table",
                "-conf": "3",
                "-name": "ftp"
              }
            },
            {
              "-protocol": "tcp",
              "-portid": "22",
              "state": {
                "-reason": "syn-ack",
                "-state": "open",
                "-reason_ttl": "45"
              },
              "service": {
                "-product": "OpenSSH",
                "-name": "ssh",
                "-extrainfo": "protocol 2.0",
                "-version": "7.9p1 Debian 10+deb10u2",
                "-conf": "10",
                "-method": "probed"
              }
            },
            {
              "-protocol": "tcp",
              "-portid": "43",
              "state": {
                "-reason": "reset",
                "-state": "closed",
                "-reason_ttl": "45"
              },
              "service": {
                "-method": "table",
                "-conf": "3",
                "-name": "whois"
              }
            },
            {
              "-protocol": "tcp",
              "-portid": "53",
              "state": {
                "-reason": "syn-ack",
                "-state": "open",
                "-reason_ttl": "45"
              },
              "service": {
                "-product": "ISC BIND",
                "-name": "domain",
                "-extrainfo": "Debian Linux",
                "-version": "9.11.5-P4-5.1+deb10u1",
                "-conf": "10",
                "-method": "probed"
              }
            },
            {
              "-protocol": "tcp",
              "-portid": "79",
              "state": {
                "-reason": "reset",
                "-state": "closed",
                "-reason_ttl": "45"
              },
              "service": {
                "-method": "table",
                "-conf": "3",
                "-name": "finger"
              }
            },
            {
              "-protocol": "tcp",
              "-portid": "80",
              "state": {
                "-reason": "syn-ack",
                "-state": "open",
                "-reason_ttl": "45"
              },
              "service": {
                "-product": "OpenResty web app server",
                "-version": "1.15.8.1",
                "-method": "probed",
                "-conf": "10",
                "-name": "http"
              }
            },
            {
              "-protocol": "tcp",
              "-portid": "110",
              "state": {
                "-reason": "reset",
                "-state": "closed",
                "-reason_ttl": "45"
              },
              "service": {
                "-method": "table",
                "-conf": "3",
                "-name": "pop3"
              }
            },
            {
              "-protocol": "tcp",
              "-portid": "119",
              "state": {
                "-reason": "reset",
                "-state": "closed",
                "-reason_ttl": "45"
              },
              "service": {
                "-method": "table",
                "-conf": "3",
                "-name": "nntp"
              }
            },
            {
              "-protocol": "tcp",
              "-portid": "143",
              "state": {
                "-reason": "reset",
                "-state": "closed",
                "-reason_ttl": "45"
              },
              "service": {
                "-method": "table",
                "-conf": "3",
                "-name": "imap"
              }
            },
            {
              "-protocol": "tcp",
              "-portid": "443",
              "state": {
                "-reason": "syn-ack",
                "-state": "open",
                "-reason_ttl": "45"
              },
              "service": {
                "-product": "OpenResty web app server",
                "-version": "1.15.8.1",
                "-method": "probed",
                "-conf": "10",
                "-name": "http"
              }
            },
            {
              "-protocol": "tcp",
              "-portid": "993",
              "state": {
                "-reason": "reset",
                "-state": "closed",
                "-reason_ttl": "45"
              },
              "service": {
                "-method": "table",
                "-conf": "3",
                "-name": "imaps"
              }
            },
            {
              "-protocol": "tcp",
              "-portid": "995",
              "state": {
                "-reason": "reset",
                "-state": "closed",
                "-reason_ttl": "45"
              },
              "service": {
                "-method": "table",
                "-conf": "3",
                "-name": "pop3s"
              }
            },
            {
              "-protocol": "tcp",
              "-portid": "3389",
              "state": {
                "-reason": "reset",
                "-state": "closed",
                "-reason_ttl": "45"
              },
              "service": {
                "-method": "table",
                "-conf": "3",
                "-name": "ms-wbt-server"
              }
            },
            {
              "-protocol": "tcp",
              "-portid": "6668",
              "state": {
                "-reason": "reset",
                "-state": "closed",
                "-reason_ttl": "45"
              },
              "service": {
                "-method": "table",
                "-conf": "3",
                "-name": "irc"
              }
            },
            {
              "-protocol": "tcp",
              "-portid": "6669",
              "state": {
                "-reason": "reset",
                "-state": "closed",
                "-reason_ttl": "45"
              },
              "service": {
                "-method": "table",
                "-conf": "3",
                "-name": "irc"
              }
            }
          ]
        },
        "os": {
          "portused": [
            {
              "-state": "open",
              "-portid": "22",
              "-proto": "tcp"
            },
            {
              "-state": "closed",
              "-portid": "21",
              "-proto": "tcp"
            }
          ]
        },
        "uptime": {
          "-lastboot": "Tue Mar  8 01:53:53 2022",
          "-seconds": "777395"
        },
        "tcpsequence": {
          "-index": "262",
          "-values": "6F64CD1,663A593B,55845473,CF9FD526,5773897C,CFA50F2B",
          "-difficulty": "Good luck!"
        },
        "ipidsequence": {
          "-values": "0,0,0,0,0,0",
          "-class": "All zeros"
        },
        "tcptssequence": {
          "-values": "CB8D8AA3,CB8D8B23,CB8D8B83,CB8D8BE3,CB8D8463,CB8D84E7",
          "-class": "other"
        },
        "trace": {
          "-port": "80",
          "-proto": "tcp",
          "hop": [
            {
              "-rtt": "2.00",
              "-host": "",
              "-ipaddr": "192.168.1.1",
              "-ttl": "1"
            },
            {
              "-rtt": "6.00",
              "-host": "",
              "-ipaddr": "100.96.0.1",
              "-ttl": "2"
            },
            {
              "-rtt": "5.00",
              "-host": "eth13.bpi.tls1b-bcr01.myaisfibre.com",
              "-ipaddr": "49.228.2.42",
              "-ttl": "3"
            },
            {
              "-rtt": "5.00",
              "-host": "ae22.bgw01j.tls1a.myaisfibre.com",
              "-ipaddr": "49.228.6.28",
              "-ttl": "4"
            },
            {
              "-rtt": "5.00",
              "-host": "",
              "-ipaddr": "161.200.116.30",
              "-ttl": "5"
            }
          ]
        }
      },
      "runstats": {
        "finished": {
          "-timestr": "Thu Mar 17 01:50:28 2022",
          "-time": "1647456628"
        },
        "hosts": {
          "-down": "0",
          "-total": "1",
          "-up": "1"
        }
      }
    },
    "#encoding": "iso-8859-1"
  }